kfn/__init__.py
kfn/imports.py
kfn/injected_code.py
kfn/kf_notebook_runner.py
kfn/lib.py
kfn/nb_component_builder.py
kfn/test/__init__.py
kfn/test/kf_notebook_runner_test.py
kfn/test/lib.py
kfn/test/nb_component_builder_test.py
kfn/test/notebooks_source.py
kfn-0.1.dist-info/LICENSE
kfn-0.1.dist-info/METADATA
kfn-0.1.dist-info/WHEEL
kfn-0.1.dist-info/top_level.txt
kfn-0.1.dist-info/RECORD
