Metadata-Version: 2.1
Name: kfn
Version: 0.1
Summary: Kubeflow notebook component builder
Home-page: https://github.com/bartgras/kf-notebook-component
Author: Bart Grasza
Author-email: bartgras@protonmail.com
License: MIT
Platform: UNKNOWN
Requires-Dist: kfp
Requires-Dist: papermill
Requires-Dist: jupytext
Requires-Dist: nbconvert
